jupyterhub_fancy_profiles/__init__.py
jupyterhub_fancy_profiles/_version.py
jupyterhub_fancy_profiles/static/dist/form.js
jupyterhub_fancy_profiles/static/dist/form.js.map
jupyterhub_fancy_profiles/static/dist/node_modules_xterm-addon-fit_lib_xterm-addon-fit_js.form.js
jupyterhub_fancy_profiles/static/dist/node_modules_xterm-addon-fit_lib_xterm-addon-fit_js.form.js.map
jupyterhub_fancy_profiles/static/dist/vendors-node_modules_jupyterhub_binderhub-client_lib_client_js.form.js
jupyterhub_fancy_profiles/static/dist/vendors-node_modules_jupyterhub_binderhub-client_lib_client_js.form.js.map
jupyterhub_fancy_profiles/static/dist/vendors-node_modules_xterm_lib_xterm_js.form.js
jupyterhub_fancy_profiles/static/dist/vendors-node_modules_xterm_lib_xterm_js.form.js.map
jupyterhub_fancy_profiles/templates/form.html
jupyterhub_fancy_profiles-0.6.0.dist-info/licenses/LICENSE
jupyterhub_fancy_profiles-0.6.0.dist-info/METADATA
jupyterhub_fancy_profiles-0.6.0.dist-info/WHEEL
jupyterhub_fancy_profiles-0.6.0.dist-info/top_level.txt
jupyterhub_fancy_profiles-0.6.0.dist-info/RECORD
