Metadata-Version: 2.4
Name: jupyterhub-fancy-profiles
Version: 0.6.0
Summary: Fancy Profile UI for jupyterhub-kubespawner
Author-email: Yuvi <yuvipanda@gmail.com>
Keywords: jupyterhub
Classifier: Programming Language :: Python :: 3
Classifier: License :: OSI Approved :: BSD License
Classifier: Operating System :: OS Independent
License-File: LICENSE
Dynamic: license-file
